ChangeLog
MANIFEST.in
README.rst
gdbm-compat-convert
setup.py
doc/gdbm_compat.html
gdbm_compat/__init__.py
gdbm_compat.egg-info/PKG-INFO
gdbm_compat.egg-info/SOURCES.txt
gdbm_compat.egg-info/dependency_links.txt
gdbm_compat.egg-info/top_level.txt