Metadata-Version: 1.1
Name: gdbm-compat
Version: 3.0.0
Summary: Allows using gdbm files created with version 1.8 or 1.10, without magic number errors.
Home-page: UNKNOWN
Author: Tim Savannah
Author-email: kata198@gmail.com
License: Public Domain
Keywords: gdbm,1.8,1.10,compat,bad,magic,number,traceback,el6,el7,centos,open,database
Platform: UNKNOWN
Classifier: Development Status :: 5 - Production/Stable
Classifier: Programming Language :: Python
Classifier: License :: Public Domain
Classifier: Programming Language :: Python :: 2
Classifier: Programming Language :: Python :: 2
Classifier: Programming Language :: Python :: 2.6
Classifier: Programming Language :: Python :: 2.7
Classifier: Programming Language :: Python :: 3
Classifier: Programming Language :: Python :: 3.3
Classifier: Programming Language :: Python :: 3.4
Classifier: Topic :: Software Development :: Libraries :: Python Modules
